<work-flow name="job_1" creator="Kent" mail-receivers="15018735011@163.com"
    dir="/example/依赖" desc="工作流实例1">
  <!-- 调度配置 -->
  <coordinator is-enabled="true">
      <depend-list cron="*/20 * * * *"></depend-list>
      <param-list>
          <param name="stadate" value="${time.today|yyyy-MM-dd|-1 day}"/>
          <param name="cnt" value="2"/>
      </param-list>
  </coordinator>
  <!-- 节点列表 -->
  <start name="start" to="data_monitor" />

  <action name="data_monitor" desc="监控" is-ignore="true">
      <data-monitor>
          <source type="COMMAND">cat /etc/profile | wc -l</source>
          <min type="NUM">2</min>
      </data-monitor>
      <ok to="script"/>
  </action>

  <action name="script" desc = "执行脚本">
      <script>
          <code><![CDATA[
            for i in `seq 0 ${param:cnt}`;do
                sleep 6
                echo -e "$i  -> ${param:stadate} -> job_1";
            done
          ]]></code>
      </script>
      <ok to="end"></ok>
  </action>

  <end name="end"/>
</work-flow>